assault_and_battery/__init__.py
assault_and_battery/cli.py
assault_and_battery/yamspy.py
assault_and_battery-0.1.4.dist-info/LICENSE
assault_and_battery-0.1.4.dist-info/entry_points.txt
assault_and_battery-0.1.4.dist-info/METADATA
assault_and_battery-0.1.4.dist-info/WHEEL
assault_and_battery-0.1.4.dist-info/RECORD
