Metadata-Version: 2.1
Name: assault-and-battery
Version: 0.1.4
Summary: A battery discharge curve calculator slash torture test.
Home-page: https://gitlab.com/stavros/assault-and-battery/
License: AGPL-3.0-or-later
Author: Stavros Korokithakis
Author-email: hi@stavros.io
Requires-Python: >=3.8,<4.0
Classifier: License :: OSI Approved :: GNU Affero General Public License v3 or later (AGPLv3+)
Classifier: Programming Language :: Python :: 3
Classifier: Programming Language :: Python :: 3.8
Classifier: Programming Language :: Python :: 3.9
Classifier: Programming Language :: Python :: 3.10
Classifier: Programming Language :: Python :: 3.11
Requires-Dist: matplotlib (>=3.4.3,<4.0.0)
Requires-Dist: pyserial (>=3.5,<4.0)
Project-URL: Repository, https://gitlab.com/stavros/assault-and-battery/
